scribo/__about__.py
scribo/__init__.py
scribo/__main__.py
scribo/build.py
scribo/copy_and_minimize.py
scribo/helper.py
scribo/pinit.py
scribo/render.py
scribo/project_template/index.md
scribo/project_template/meta.json
scribo/project_template/assets/fonts/Montserrat-Regular.ttf
scribo/project_template/assets/fonts/remixicon.svg
scribo/project_template/assets/fonts/remixicon.ttf
scribo/project_template/assets/scripts/script.js
scribo/project_template/assets/static/icon.png
scribo/project_template/assets/styles/remixicon.css
scribo/project_template/assets/styles/style.css
scribo/project_template/assets/styles/theme.css
scribo/project_template/assets/templates/base.html.jinja
scribo/project_template/assets/templates/footer.html.jinja
scribo/project_template/assets/templates/header.html.jinja
scribo/project_template/assets/templates/index.html.jinja
scribo/project_template/assets/templates/sitemap.html.jinja
scribo/project_template/assets/templates/toc.html.jinja
scribo/project_template/pages/about/index.md
scribo/project_template/pages/getting started/index.md
scribo-1.0.0.dist-info/METADATA
scribo-1.0.0.dist-info/WHEEL
scribo-1.0.0.dist-info/entry_points.txt
scribo-1.0.0.dist-info/licenses/AUTHORS.md
scribo-1.0.0.dist-info/licenses/LICENSE
scribo-1.0.0.dist-info/licenses/NOTICE
scribo-1.0.0.dist-info/RECORD
