Metadata-Version: 2.4
Name: scribo
Version: 1.0.0
Summary: A simple, efficient and content-first static site generator (SSG).
Project-URL: Documentation, https://github.com/sujaudd1n/scribo#readme
Project-URL: Issues, https://github.com/sujaudd1n/scribo/issues
Project-URL: Source, https://github.com/sujaudd1n/scribo
Author: Md Sujauddin Sekh
License-Expression: MIT
License-File: AUTHORS.md
License-File: LICENSE
License-File: NOTICE
Keywords: documentation,jinja,markdown,scribo,static-site-generator
Classifier: Development Status :: 4 - Beta
Classifier: Programming Language :: Python
Classifier: Programming Language :: Python :: 3.8
Classifier: Programming Language :: Python :: 3.9
Classifier: Programming Language :: Python :: 3.10
Classifier: Programming Language :: Python :: 3.11
Classifier: Programming Language :: Python :: 3.12
Classifier: Programming Language :: Python :: Implementation :: CPython
Classifier: Programming Language :: Python :: Implementation :: PyPy
Requires-Python: >=3.8
Requires-Dist: iniconfig==2.0.0
Requires-Dist: jinja2==3.1.4
Requires-Dist: markdown==3.6
Requires-Dist: markupsafe==2.1.5
Requires-Dist: minify-html==0.15.0
Requires-Dist: packaging==24.1
Requires-Dist: pluggy==1.5.0
Requires-Dist: pygments==2.18.0
